llms/__init__.py
llms/gemini_llm.py
llms/openai_llm.py
llms_Arunsingh-0.1.0.dist-info/METADATA
llms_Arunsingh-0.1.0.dist-info/WHEEL
llms_Arunsingh-0.1.0.dist-info/top_level.txt
llms_Arunsingh-0.1.0.dist-info/RECORD
